{ "SKUs":[
  {
    "id": "810",
    "code": "=203700",
    "name": "Балтика Классическое Традиционное №3",
    "kind": 32770,
    "brand": "60",
    "volume": "0.45000000000000001",
    "width": "64",
    "height": "168",
    "pict": "=203700.png",
    "unit": "1",
    "order": "1000",
    "liter": "0",
    "brand_name": "Балтика 3",
    "brand_weight": "44",
    "rank": 1,
    "sales": 29077.29,
    "sales_r": 5079258.1806,
    "mml": 1,
    "useful": "2",
    "group": "mml",
    "category_group": "Пиво",
    "sub_sales": 0,
    "sub_sales_r": 0,
    "sku_region": 1,
    "basket": "",
    "sku_min": 0,
    "sku_max": 3
  },
  {
    "id": "809",
    "code": "=209700",
    "name": "Балтика экспортное Премиум №7 ",
    "kind": 32770,
    "brand": "63",
    "volume": "0.45000000000000001",
    "width": "64",
    "height": "168",
    "pict": "=209700.png",
    "unit": "1",
    "order": "1000",
    "liter": "0",
    "brand_name": "Балтика 7",
    "brand_weight": "48",
    "rank": 7,
    "sales": 18267.525,
    "sales_r": 3170088.5599,
    "mml": 1,
    "useful": "2",
    "group": "mml",
    "category_group": "Пиво",
    "sub_sales": 0,
    "sub_sales_r": 0,
    "sku_region": 1,
    "basket": "",
    "sku_min": 0,
    "sku_max": 3
  },
  {
    "id": "594",
    "code": "=330700",
    "name": "Carlsberg",
    "kind": 32770,
    "brand": "5",
    "volume": "0.45000000000000001",
    "width": "64",
    "height": "169",
    "pict": "=330700.png",
    "unit": "1",
    "order": "59",
    "liter": "0",
    "brand_name": "Carlsberg",
    "brand_weight": "8",
    "rank": 9,
    "sales": 15534.54,
    "sales_r": 1647156.4458,
    "mml": 1,
    "useful": "2",
    "group": "mml",
    "category_group": "Пиво",
    "sub_sales": 0,
    "sub_sales_r": 0,
    "sku_region": 1,
    "basket": "",
    "sku_min": "2",
    "sku_max": "3"
  },
  {
    "id": "581",
    "code": "=009700",
    "name": "Балтика №9",
    "kind": 32770,
    "brand": "64",
    "volume": "0.45000000000000001",
    "width": "64",
    "height": "169",
    "pict": "=009700.png",
    "unit": "1",
    "order": "92",
    "liter": "0",
    "brand_name": "Балтика 9",
    "brand_weight": "49",
    "rank": 10,
    "sales": 11813.13,
    "sales_r": 2001445.341,
    "mml": 1,
    "useful": "2",
    "group": "mml",
    "category_group": "Пиво",
    "sub_sales": 0,
    "sub_sales_r": 0,
    "sku_region": 1,
    "basket": "",
    "sku_min": "2",
    "sku_max": "3"
  },
  {
    "id": "625",
    "code": "=330610",
    "name": "Carlsberg",
    "kind": 32769,
    "brand": "5",
    "volume": "0.47999999999999998",
    "width": "69",
    "height": "263",
    "pict": "=330610.png",
    "unit": "1",
    "order": "109",
    "liter": "0",
    "brand_name": "Carlsberg",
    "brand_weight": "8",
    "rank": 12,
    "sales": 11997.216,
    "sales_r": 1204905.9429,
    "mml": 1,
    "useful": "2",
    "group": "mml",
    "category_group": "Пиво",
    "sub_sales": 0,
    "sub_sales_r": 0,
    "sku_region": 1,
    "basket": "",
    "sku_min": "2",
    "sku_max": "3"
  },
  {
    "id": "815",
    "code": "=508610",
    "name": "Zatecky Gus Cesky",
    "kind": 32769,
    "brand": "68",
    "volume": "0.47999999999999998",
    "width": "68",
    "height": "273",
    "pict": "=508610.png",
    "unit": "1",
    "order": "1000",
    "liter": "0",
    "brand_name": "Zatecky Gus",
    "brand_weight": "35",
    "rank": 14,
    "sales": 8947.632,
    "sales_r": 1297466.0404,
    "mml": 1,
    "useful": "2",
    "group": "mml",
    "category_group": "Пиво",
    "sub_sales": 0,
    "sub_sales_r": 0,
    "sku_region": 1,
    "basket": "",
    "sku_min": 0,
    "sku_max": 3
  },
  {
    "id": "554",
    "code": "=000700",
    "name": "Балтика №0",
    "kind": 32770,
    "brand": "58",
    "volume": "0.45000000000000001",
    "width": "64",
    "height": "169",
    "pict": "=000700.png",
    "unit": "1",
    "order": "75",
    "liter": "0",
    "brand_name": "Балтика 0",
    "brand_weight": "42",
    "rank": 15,
    "sales": 7691.355,
    "sales_r": 2426983.2062,
    "mml": 1,
    "useful": "2",
    "group": "mml",
    "category_group": "Пиво",
    "sub_sales": 0,
    "sub_sales_r": 0,
    "sku_region": 1,
    "basket": "",
    "sku_min": "2",
    "sku_max": "3"
  },
  {
    "id": "811",
    "code": "=508811",
    "name": "Zatecky Gus Cesky",
    "kind": 32772,
    "brand": "68",
    "volume": "1.3500000000000001",
    "width": "91",
    "height": "332",
    "pict": "=508811.png",
    "unit": "1",
    "order": "93",
    "liter": "0",
    "brand_name": "Zatecky Gus",
    "brand_weight": "35",
    "rank": 17,
    "sales": 8536.918,
    "sales_r": 802619.5816,
    "mml": 1,
    "useful": "2",
    "group": "mml",
    "category_group": "Пиво",
    "sub_sales": 0,
    "sub_sales_r": 0,
    "sku_region": 1,
    "basket": "",
    "sku_min": 0,
    "sku_max": 2
  },
  {
    "id": "628",
    "code": "=380610",
    "name": "Tuborg Green",
    "kind": 32769,
    "brand": "24",
    "volume": "0.47999999999999998",
    "width": "70",
    "height": "264",
    "pict": "=380610.png",
    "unit": "1",
    "order": "43",
    "liter": "0",
    "brand_name": "Tuborg",
    "brand_weight": "32",
    "rank": 21,
    "sales": 6838.368,
    "sales_r": 1125794.1939,
    "mml": 1,
    "useful": "2",
    "group": "mml",
    "category_group": "Пиво",
    "sub_sales": 0,
    "sub_sales_r": 0,
    "sku_region": 1,
    "basket": "",
    "sku_min": "2",
    "sku_max": "3"
  },
  {
    "id": "812",
    "code": "=209811",
    "name": "Балтика экспортное Премиум №7",
    "kind": 32772,
    "brand": "63",
    "volume": "1.3500000000000001",
    "width": "91",
    "height": "332",
    "pict": "=209811.png",
    "unit": "1",
    "order": "184",
    "liter": "0",
    "brand_name": "Балтика 7",
    "brand_weight": "48",
    "rank": 33,
    "sales": 3905.685,
    "sales_r": 620743.8501,
    "mml": 1,
    "useful": "2",
    "group": "mml",
    "category_group": "Пиво",
    "sub_sales": 0,
    "sub_sales_r": 0,
    "sku_region": 1,
    "basket": "",
    "sku_min": 0,
    "sku_max": 2
  },
  {
    "id": "232",
    "code": "=641320",
    "name": "Flash Up Max",
    "kind": 16388,
    "brand": "10",
    "volume": "1.0",
    "width": "80",
    "height": "290",
    "pict": "=641320.png",
    "unit": "1",
    "order": "730",
    "liter": "0",
    "brand_name": "Flash",
    "brand_weight": "14",
    "rank": 2,
    "sales": 23793.1,
    "sales_r": 4171864.3141,
    "mml": 0,
    "useful": "1",
    "group": "Flash",
    "category_group": "Не Пиво",
    "sub_sales": 0,
    "sub_sales_r": 0,
    "sku_region": 1,
    "basket": "",
    "sku_min": 0,
    "sku_max": 2
  }
]
}
